ogdf_wheel-2023.9.data/data/include/coin/CoinAlloc.hpp
ogdf_wheel-2023.9.data/data/include/coin/ClpCholeskyWssmp.hpp
ogdf_wheel-2023.9.data/data/include/coin/ClpPrimalColumnPivot.hpp
ogdf_wheel-2023.9.data/data/include/coin/CoinFactorization.hpp
ogdf_wheel-2023.9.data/data/include/coin/ClpPackedMatrix.hpp
ogdf_wheel-2023.9.data/data/include/coin/OsiRowCutDebugger.hpp
ogdf_wheel-2023.9.data/data/include/coin/OsiSolverParameters.hpp
ogdf_wheel-2023.9.data/data/include/coin/CoinDistance.hpp
ogdf_wheel-2023.9.data/data/include/coin/CoinParam.hpp
ogdf_wheel-2023.9.data/data/include/coin/ClpDynamicExampleMatrix.hpp
ogdf_wheel-2023.9.data/data/include/coin/OsiSolverBranch.hpp
ogdf_wheel-2023.9.data/data/include/coin/MyMessageHandler.hpp
ogdf_wheel-2023.9.data/data/include/coin/ClpMessage.hpp
ogdf_wheel-2023.9.data/data/include/coin/CoinStructuredModel.hpp
ogdf_wheel-2023.9.data/data/include/coin/ClpDummyMatrix.hpp
ogdf_wheel-2023.9.data/data/include/coin/CoinMpsIO.hpp
ogdf_wheel-2023.9.data/data/include/coin/CoinLpIO.hpp
ogdf_wheel-2023.9.data/data/include/coin/ClpEventHandler.hpp
ogdf_wheel-2023.9.data/data/include/coin/ClpConstraintQuadratic.hpp
ogdf_wheel-2023.9.data/data/include/coin/ClpSimplexPrimal.hpp
ogdf_wheel-2023.9.data/data/include/coin/ClpCholeskyMumps.hpp
ogdf_wheel-2023.9.data/data/include/coin/CoinPresolveSubst.hpp
ogdf_wheel-2023.9.data/data/include/coin/OsiGrbSolverInterface.hpp
ogdf_wheel-2023.9.data/data/include/coin/ClpSimplexDual.hpp
ogdf_wheel-2023.9.data/data/include/coin/CoinWarmStartVector.hpp
ogdf_wheel-2023.9.data/data/include/coin/ClpSimplexOther.hpp
ogdf_wheel-2023.9.data/data/include/coin/CoinModel.hpp
ogdf_wheel-2023.9.data/data/include/coin/ClpSimplex.hpp
ogdf_wheel-2023.9.data/data/include/coin/CoinSnapshot.hpp
ogdf_wheel-2023.9.data/data/include/coin/OsiCut.hpp
ogdf_wheel-2023.9.data/data/include/coin/config_coinutils_default.h
ogdf_wheel-2023.9.data/data/include/coin/ClpConstraint.hpp
ogdf_wheel-2023.9.dist-info/RECORD
ogdf_wheel-2023.9.dist-info/WHEEL
ogdf_wheel-2023.9.dist-info/METADATA
ogdf_wheel-2023.9.dist-info/licenses/ogdf/LICENSE.txt
ogdf_wheel-2023.9.dist-info/licenses/ogdf/LICENSE_GPL_v3.txt
ogdf_wheel-2023.9.dist-info/licenses/ogdf/LICENSE_GPL_v2.txt
ogdf_wheel-2023.9.dist-info/licenses/ogdf/include/ogdf/lib/minisat/LICENSE
