Metadata-Version: 2.1
Name: ogdf-wheel
Version: 2023.9
Summary: An OGDF release build packaged as ready-to-use python wheel.
License-File: ogdf/LICENSE.txt
License-File: ogdf/LICENSE_GPL_v2.txt
License-File: ogdf/LICENSE_GPL_v3.txt
License-File: ogdf/include/ogdf/lib/minisat/LICENSE
Classifier: Programming Language :: Python :: 3
Requires-Python: >=3.7
